backrun/__init__.py
backrun-0.0.9.dist-info/METADATA
backrun-0.0.9.dist-info/WHEEL
backrun-0.0.9.dist-info/entry_points.txt
backrun-0.0.9.dist-info/licenses/LICENSE
backrun-0.0.9.dist-info/RECORD
