Metadata-Version: 2.3
Name: backrun
Version: 0.0.9
Summary: Run other programs in background
Project-URL: Homepage, https://github.com/yaroslaff/backrun
Project-URL: Issues, https://github.com/yaroslaff/backrun/issues
Author-email: Yaroslav Polyakov <yaroslaff@gmail.com>
License-File: LICENSE
Classifier: License :: OSI Approved :: MIT License
Classifier: Operating System :: OS Independent
Classifier: Programming Language :: Python :: 3
Requires-Python: >=3.9
Requires-Dist: inotify
Requires-Dist: loguru
Requires-Dist: toml
